setup.py
fxa_client/__init__.py
fxa_client/fxa_client.py
fxa_client/fxa_crypto.py
fxa_client/fxa_vectors.py
fxa_client/hkdf.py
fxa_client/pbkdf2.py
fxa_python_client.egg-info/PKG-INFO
fxa_python_client.egg-info/SOURCES.txt
fxa_python_client.egg-info/dependency_links.txt
fxa_python_client.egg-info/entry_points.txt
fxa_python_client.egg-info/requires.txt
fxa_python_client.egg-info/top_level.txt