Metadata-Version: 1.1
Name: fxa-python-client
Version: 1.2.0
Summary: python sample code to access Firefox Account (FxA) APIs
Home-page: https://github.com/mozilla/fxa-python-client
Author: Ryan Kelly
Author-email: rfkelly@mozilla.com
License: UNKNOWN
Platform: UNKNOWN
Classifier: Programming Language :: Python
Classifier: Programming Language :: Python :: 2
Classifier: Programming Language :: Python :: 2.7
Classifier: Programming Language :: Python :: 3
Classifier: Programming Language :: Python :: 3.2
Classifier: Programming Language :: Python :: 3.3
